xsltproc_py_lite/xsltproc_py.py
xsltproc_py_lite-0.1.2.dist-info/licenses/LICENSE
xsltproc_py_lite-0.1.2.dist-info/METADATA
xsltproc_py_lite-0.1.2.dist-info/WHEEL
xsltproc_py_lite-0.1.2.dist-info/entry_points.txt
xsltproc_py_lite-0.1.2.dist-info/top_level.txt
xsltproc_py_lite-0.1.2.dist-info/RECORD
