Metadata-Version: 2.4
Name: xsltproc-py-lite
Version: 0.1.2
Summary: A lightweight Python+lxml implementation of xsltproc with limited features
Author-email: Takaaki AOKI <aoki.takaaki@gmail.com>
License-Expression: MIT
License-File: LICENSE
Requires-Dist: lxml
Dynamic: license-file
